Metadata-Version: 2.1
Name: kockatykalendar
Version: 0.1.1
Summary: API, tools and utilities for working with KockatyKalendar.sk
Home-page: https://github.com/kockatykalendar/python
Author: Adam Zahradník
Author-email: adam@zahradnik.xyz
License: MIT
Platform: UNKNOWN
Classifier: Development Status :: 2 - Pre-Alpha
Classifier: License :: OSI Approved :: MIT License
Classifier: Intended Audience :: Developers
Classifier: Programming Language :: Python
Classifier: Programming Language :: Python :: 3
Provides-Extra: django
Provides-Extra: api
